src/__init__.py
src/main.py
src/templates/c#/Dockerfile.j2
src/templates/c#/docker-compose.yml.j2
src/templates/go/Dockerfile.j2
src/templates/go/docker-compose.yml.j2
src/templates/java/Dockerfile.j2
src/templates/java/docker-compose.yml.j2
src/templates/node/Dockerfile.j2
src/templates/node/docker-compose.yml.j2
src/templates/python/Dockerfile.j2
src/templates/python/docker-compose.yml.j2
src/templates/rust/Dockerfile.j2
src/templates/rust/docker-compose.yml.j2
podman_init-1.0.3.dist-info/LICENSE
podman_init-1.0.3.dist-info/METADATA
podman_init-1.0.3.dist-info/WHEEL
podman_init-1.0.3.dist-info/entry_points.txt
podman_init-1.0.3.dist-info/top_level.txt
podman_init-1.0.3.dist-info/RECORD
