Metadata-Version: 2.1
Name: podman-init
Version: 1.0.3
Summary: Python command-line tool that automates the process of initializing Docker-related files for your projects.
Home-page: https://github.com/suriya-mca/Podman_Init_Cli
Author: Suriya
License: MIT
Classifier: Programming Language :: Python :: 3
Classifier: License :: OSI Approved :: MIT License
Classifier: Operating System :: OS Independent
License-File: LICENSE
Requires-Dist: click
Requires-Dist: jinja2
